example_sv_verilator/hdl/MyTopLevel.v
// Generator : SpinalHDL v1.7.0a    git head : 150a9b9067020722818dfb17df4a23ac712a7af8
// Component : MyTopLevel
// Git hash  : 23f8152f1f76822abe6de05999e6f5a903223b02

`timescale 1ns/1ps

module MyTopLevel (
  input      [7:0]    io_A,
  input      [7:0]    io_B,
  output     [7:0]    io_X,
  input               clk,
  input               reset
);

  reg        [7:0]    a;
  reg        [7:0]    b;
  wire                when_MyTopLevel_l36;

  assign when_MyTopLevel_l36 = 1'b1;
  assign io_X = (a + b);
  always @(posedge clk or posedge reset) begin
    if(reset) begin
      a <= 8'h0;
      b <= 8'h0;
    end else begin
      if(when_MyTopLevel_l36) begin
        a <= io_A;
        b <= io_B;
      end
    end
  end

export "DPI-C" function sv_print;

function void sv_print();
    $display("sv side : print\n");
endfunction

endmodule

test.vcd
$version Generated by VerilatedVcd $end
$date Mon Jul 11 18:20:59 2022
 $end
$timescale   1ps $end

 $scope module TOP $end
  $var wire  1 & clk $end
  $var wire  8 # io_A [7:0] $end
  $var wire  8 $ io_B [7:0] $end
  $var wire  8 % io_X [7:0] $end
  $var wire  1 ' reset $end
  $scope module MyTopLevel $end
   $var wire  8 ( a [7:0] $end
   $var wire  8 ) b [7:0] $end
   $var wire  1 & clk $end
   $var wire  8 # io_A [7:0] $end
   $var wire  8 $ io_B [7:0] $end
   $var wire  8 % io_X [7:0] $end
   $var wire  1 ' reset $end
   $var wire  1 * when_MyTopLevel_l36 $end
  $upscope $end
 $upscope $end
$enddefinitions $end


#0
b00001010 #
b00110010 $
b00000000 %
0&
1'
b00000000 (
b00000000 )
1*
#160
0'
#170
b00001011 #
b00110011 $
b00111100 %
1&
b00001010 (
b00110010 )
#175
0&
#180
b00001100 #
b00110100 $
b00111110 %
1&
b00001011 (
b00110011 )
#185
0&
#190
b00001101 #
b00110101 $
b01000000 %
1&
b00001100 (
b00110100 )
#195
0&
#200
b00001110 #
b00110110 $
b01000010 %
1&
b00001101 (
b00110101 )
#205
0&
#210
b00001111 #
b00110111 $
b01000100 %
1&
b00001110 (
b00110110 )
#215
0&
#220
b00010000 #
b00111000 $
b01000110 %
1&
b00001111 (
b00110111 )
#225
0&
#230
b00010001 #
b00111001 $
b01001000 %
1&
b00010000 (
b00111000 )
#235
0&
#240
b00010010 #
b00111010 $
b01001010 %
1&
b00010001 (
b00111001 )
#245
0&
#250
b00010011 #
b00111011 $
b01001100 %
1&
b00010010 (
b00111010 )
#255
0&
#260
b00010100 #
b00111100 $
b01001110 %
1&
b00010011 (
b00111011 )
#265
0&
#270
b00010101 #
b00111101 $
b01010000 %
1&
b00010100 (
b00111100 )
#275
0&
#280
b00010110 #
b00111110 $
b01010010 %
1&
b00010101 (
b00111101 )
#285
0&
#290
b00010111 #
b00111111 $
b01010100 %
1&
b00010110 (
b00111110 )
#295
0&
#300
b00011000 #
b01000000 $
b01010110 %
1&
b00010111 (
b00111111 )
#305
0&
#310
b00011001 #
b01000001 $
b01011000 %
1&
b00011000 (
b01000000 )
#315
0&
#320
b00011010 #
b01000010 $
b01011010 %
1&
b00011001 (
b01000001 )
#325
0&
#330
b00011011 #
b01000011 $
b01011100 %
1&
b00011010 (
b01000010 )
#335
0&
#340
b00011100 #
b01000100 $
b01011110 %
1&
b00011011 (
b01000011 )
#345
0&
#350
b00011101 #
b01000101 $
b01100000 %
1&
b00011100 (
b01000100 )
#355
0&
#360
b00011110 #
b01000110 $
b01100010 %
1&
b00011101 (
b01000101 )
#365
0&
#370
b00011111 #
b01000111 $
b01100100 %
1&
b00011110 (
b01000110 )
#375
0&
#380
b00100000 #
b01001000 $
b01100110 %
1&
b00011111 (
b01000111 )
#385
0&
#390
b00100001 #
b01001001 $
b01101000 %
1&
b00100000 (
b01001000 )
#395
0&
#400
b00100010 #
b01001010 $
b01101010 %
1&
b00100001 (
b01001001 )
#405
0&
#410
b00100011 #
b01001011 $
b01101100 %
1&
b00100010 (
b01001010 )
#415
0&
#420
b00100100 #
b01001100 $
b01101110 %
1&
b00100011 (
b01001011 )
#425
0&
#430
b00100101 #
b01001101 $
b01110000 %
1&
b00100100 (
b01001100 )
#435
0&
#440
b00100110 #
b01001110 $
b01110010 %
1&
b00100101 (
b01001101 )
#445
0&
#450
b00100111 #
b01001111 $
b01110100 %
1&
b00100110 (
b01001110 )
#455
0&
#460
b00101000 #
b01010000 $
b01110110 %
1&
b00100111 (
b01001111 )
#465
0&
#470
b00101001 #
b01010001 $
b01111000 %
1&
b00101000 (
b01010000 )
#475
0&
#480
b00101010 #
b01010010 $
b01111010 %
1&
b00101001 (
b01010001 )
#485
0&
#490
b00101011 #
b01010011 $
b01111100 %
1&
b00101010 (
b01010010 )
#495
0&
#500
b00101100 #
b01010100 $
b01111110 %
1&
b00101011 (
b01010011 )
#505
0&
#510
b00101101 #
b01010101 $
b10000000 %
1&
b00101100 (
b01010100 )
#515
0&
#520
b00101110 #
b01010110 $
b10000010 %
1&
b00101101 (
b01010101 )
#525
0&
#530
b00101111 #
b01010111 $
b10000100 %
1&
b00101110 (
b01010110 )
#535
0&
#540
b00110000 #
b01011000 $
b10000110 %
1&
b00101111 (
b01010111 )
#545
0&
#550
b00110001 #
b01011001 $
b10001000 %
1&
b00110000 (
b01011000 )
#555
0&
#560
b00110010 #
b01011010 $
b10001010 %
1&
b00110001 (
b01011001 )
#565
0&
#570
b00110011 #
b01011011 $
b10001100 %
1&
b00110010 (
b01011010 )
#575
0&
#580
b00110100 #
b01011100 $
b10001110 %
1&
b00110011 (
b01011011 )
#585
0&
#590
b00110101 #
b01011101 $
b10010000 %
1&
b00110100 (
b01011100 )
#595
0&
#600
b00110110 #
b01011110 $
b10010010 %
1&
b00110101 (
b01011101 )
#605
0&
#610
b00110111 #
b01011111 $
b10010100 %
1&
b00110110 (
b01011110 )
#615
0&
#620
b00111000 #
b01100000 $
b10010110 %
1&
b00110111 (
b01011111 )
#625
0&
#630
b00111001 #
b01100001 $
b10011000 %
1&
b00111000 (
b01100000 )
#635
0&
#640
b00111010 #
b01100010 $
b10011010 %
1&
b00111001 (
b01100001 )
#645
0&
#650
b00111011 #
b01100011 $
b10011100 %
1&
b00111010 (
b01100010 )
#655
0&
#660
b00111100 #
b01100100 $
b10011110 %
1&
b00111011 (
b01100011 )
#665
0&
#670
b00111101 #
b01100101 $
b10100000 %
1&
b00111100 (
b01100100 )
#675
0&
#680
b00111110 #
b01100110 $
b10100010 %
1&
b00111101 (
b01100101 )
#685
0&
#690
b00111111 #
b01100111 $
b10100100 %
1&
b00111110 (
b01100110 )
#695
0&
#700
b01000000 #
b01101000 $
b10100110 %
1&
b00111111 (
b01100111 )
#705
0&
#710
b01000001 #
b01101001 $
b10101000 %
1&
b01000000 (
b01101000 )
#715
0&
#720
b01000010 #
b01101010 $
b10101010 %
1&
b01000001 (
b01101001 )
#725
0&
#730
b01000011 #
b01101011 $
b10101100 %
1&
b01000010 (
b01101010 )
#735
0&
#740
b01000100 #
b01101100 $
b10101110 %
1&
b01000011 (
b01101011 )
#745
0&
#750
b01000101 #
b01101101 $
b10110000 %
1&
b01000100 (
b01101100 )
#755
0&
#760
b01000110 #
b01101110 $
b10110010 %
1&
b01000101 (
b01101101 )
#765
0&
#770
b01000111 #
b01101111 $
b10110100 %
1&
b01000110 (
b01101110 )
#775
0&
#780
b01001000 #
b01110000 $
b10110110 %
1&
b01000111 (
b01101111 )
#785
0&
#790
b01001001 #
b01110001 $
b10111000 %
1&
b01001000 (
b01110000 )
#795
0&
#800
b01001010 #
b01110010 $
b10111010 %
1&
b01001001 (
b01110001 )
#805
0&
#810
b01001011 #
b01110011 $
b10111100 %
1&
b01001010 (
b01110010 )
#815
0&
#820
b01001100 #
b01110100 $
b10111110 %
1&
b01001011 (
b01110011 )
#825
0&
#830
b01001101 #
b01110101 $
b11000000 %
1&
b01001100 (
b01110100 )
#835
0&
#840
b01001110 #
b01110110 $
b11000010 %
1&
b01001101 (
b01110101 )
#845
0&
#850
b01001111 #
b01110111 $
b11000100 %
1&
b01001110 (
b01110110 )
#855
0&
#860
b01010000 #
b01111000 $
b11000110 %
1&
b01001111 (
b01110111 )
#865
0&
#870
b01010001 #
b01111001 $
b11001000 %
1&
b01010000 (
b01111000 )
#875
0&
#880
b01010010 #
b01111010 $
b11001010 %
1&
b01010001 (
b01111001 )
#885
0&
#890
b01010011 #
b01111011 $
b11001100 %
1&
b01010010 (
b01111010 )
#895
0&
#900
b01010100 #
b01111100 $
b11001110 %
1&
b01010011 (
b01111011 )
#905
0&
#910
b01010101 #
b01111101 $
b11010000 %
1&
b01010100 (
b01111100 )
#915
0&
#920
b01010110 #
b01111110 $
b11010010 %
1&
b01010101 (
b01111101 )
#925
0&
#930
b01010111 #
b01111111 $
b11010100 %
1&
b01010110 (
b01111110 )
#935
0&
#940
b01011000 #
b10000000 $
b11010110 %
1&
b01010111 (
b01111111 )
#945
0&
#950
b01011001 #
b10000001 $
b11011000 %
1&
b01011000 (
b10000000 )
#955
0&
#960
b01011010 #
b10000010 $
b11011010 %
1&
b01011001 (
b10000001 )
#965
0&
#970
b01011011 #
b10000011 $
b11011100 %
1&
b01011010 (
b10000010 )
#975
0&
#980
b01011100 #
b10000100 $
b11011110 %
1&
b01011011 (
b10000011 )
#985
0&
#990
b01011101 #
b10000101 $
b11100000 %
1&
b01011100 (
b10000100 )
#995
0&
#1000
b01011110 #
b10000110 $
b11100010 %
1&
b01011101 (
b10000101 )
#1005
0&
#1010
b01011111 #
b10000111 $
b11100100 %
1&
b01011110 (
b10000110 )
#1015
0&
#1020
b01100000 #
b10001000 $
b11100110 %
1&
b01011111 (
b10000111 )
#1025
0&
#1030
b01100001 #
b10001001 $
b11101000 %
1&
b01100000 (
b10001000 )
#1035
0&
#1040
b01100010 #
b10001010 $
b11101010 %
1&
b01100001 (
b10001001 )
#1045
0&
#1050
b01100011 #
b10001011 $
b11101100 %
1&
b01100010 (
b10001010 )
#1055
0&
#1060
b01100100 #
b10001100 $
b11101110 %
1&
b01100011 (
b10001011 )
#1065
0&
#1070
b01100101 #
b10001101 $
b11110000 %
1&
b01100100 (
b10001100 )
#1075
0&
#1080
b01100110 #
b10001110 $
b11110010 %
1&
b01100101 (
b10001101 )
#1085
0&
#1090
b01100111 #
b10001111 $
b11110100 %
1&
b01100110 (
b10001110 )
#1095
0&
#1100
b01101000 #
b10010000 $
b11110110 %
1&
b01100111 (
b10001111 )
#1105
0&
#1110
b01101001 #
b10010001 $
b11111000 %
1&
b01101000 (
b10010000 )
#1115
0&
#1120
b01101010 #
b10010010 $
b11111010 %
1&
b01101001 (
b10010001 )
#1125
0&
#1130
b01101011 #
b10010011 $
b11111100 %
1&
b01101010 (
b10010010 )
#1135
0&
#1140
b01101100 #
b10010100 $
b11111110 %
1&
b01101011 (
b10010011 )
#1145
0&
#1150
b01101101 #
b10010101 $
b00000000 %
1&
b01101100 (
b10010100 )
#1155
0&
#1160
b01101110 #
b10010110 $
b00000010 %
1&
b01101101 (
b10010101 )
