example_sv_verilator/hdl/MyTopLevel.v
// Generator : SpinalHDL v1.7.0a    git head : 150a9b9067020722818dfb17df4a23ac712a7af8
// Component : MyTopLevel
// Git hash  : 23f8152f1f76822abe6de05999e6f5a903223b02

`timescale 1ns/1ps

module MyTopLevel (
  input      [7:0]    io_A,
  input      [7:0]    io_B,
  output     [7:0]    io_X,
  input               clk,
  input               reset
);

  reg        [7:0]    a;
  reg        [7:0]    b;
  wire                when_MyTopLevel_l36;

  assign when_MyTopLevel_l36 = 1'b1;
  assign io_X = (a + b);
  always @(posedge clk or posedge reset) begin
    if(reset) begin
      a <= 8'h0;
      b <= 8'h0;
    end else begin
      if(when_MyTopLevel_l36) begin
        a <= io_A;
        b <= io_B;
      end
    end
  end

export "DPI-C" function sv_print;

function void sv_print();
    $display("sv side : print\n");
endfunction

endmodule

example_python/example/tests/simulation/wave.vcd
$version Generated by VerilatedVcd $end
$date Wed Jul 13 01:59:52 2022
 $end
$timescale   1ps $end

 $scope module TOP $end
  $var wire  1 & clk $end
  $var wire  8 # io_A [7:0] $end
  $var wire  8 $ io_B [7:0] $end
  $var wire  8 % io_X [7:0] $end
  $var wire  1 ' reset $end
  $scope module MyTopLevel $end
   $var wire  8 ( a [7:0] $end
   $var wire  8 ) b [7:0] $end
   $var wire  1 & clk $end
   $var wire  8 # io_A [7:0] $end
   $var wire  8 $ io_B [7:0] $end
   $var wire  8 % io_X [7:0] $end
   $var wire  1 ' reset $end
   $var wire  1 * when_MyTopLevel_l36 $end
  $upscope $end
 $upscope $end
$enddefinitions $end


#0
b00000000 #
b00000000 $
b00000000 %
0&
1'
b00000000 (
b00000000 )
1*
#1
#2
#3
#4
#5
#6
#7
#8
#9
#10
#11
#12
#13
#14
#15
#16
#17
#18
#19
#20
#21
#22
#23
#24
#25
#26
#27
#28
#29
#30
#31
#32
#33
#34
#35
#36
#37
#38
#39
#40
#41
#42
#43
#44
#45
#46
#47
#48
#49
#50
#51
#52
#53
#54
#55
#56
#57
#58
#59
#60
#61
#62
#63
#64
#65
#66
#67
#68
#69
#70
#71
#72
#73
#74
#75
#76
#77
#78
#79
#80
#81
#82
#83
#84
#85
#86
#87
#88
#89
#90
#91
#92
#93
#94
#95
#96
#97
#98
#99
#100
b00000001 #
b00000001 $
b00000010 %
1&
0'
b00000001 (
b00000001 )
#101
#102
#103
#104
#105
0&
#106
#107
#108
#109
#110
b00000010 #
b00000010 $
b00000100 %
1&
b00000010 (
b00000010 )
#111
#112
#113
#114
#115
0&
#116
#117
#118
#119
#120
b00000011 #
b00000011 $
b00000110 %
1&
b00000011 (
b00000011 )
#121
#122
#123
#124
#125
0&
#126
#127
#128
#129
#130
b00000100 #
b00000100 $
b00001000 %
1&
b00000100 (
b00000100 )
#131
#132
#133
#134
#135
0&
#136
#137
#138
#139
#140
b00000101 #
b00000101 $
b00001010 %
1&
b00000101 (
b00000101 )
#141
#142
#143
#144
#145
0&
#146
#147
#148
#149
#150
b00000110 #
b00000110 $
b00001100 %
1&
b00000110 (
b00000110 )
#151
#152
#153
#154
#155
0&
#156
#157
#158
#159
#160
b00000111 #
b00000111 $
b00001110 %
1&
b00000111 (
b00000111 )
#161
#162
#163
#164
#165
0&
#166
#167
#168
#169
#170
b00001000 #
b00001000 $
b00010000 %
1&
b00001000 (
b00001000 )
#171
#172
#173
#174
#175
0&
#176
#177
#178
#179
#180
b00001001 #
b00001001 $
b00010010 %
1&
b00001001 (
b00001001 )
#181
#182
#183
#184
#185
0&
#186
#187
#188
#189
#190
b00001010 #
b00001010 $
b00010100 %
1&
b00001010 (
b00001010 )
#191
#192
#193
#194
#195
0&
#196
#197
#198
#199
#200
b00001011 #
b00001011 $
b00010110 %
1&
b00001011 (
b00001011 )
#201
#202
#203
#204
#205
0&
#206
#207
#208
#209
#210
b00001100 #
b00001100 $
b00011000 %
1&
b00001100 (
b00001100 )
#211
#212
#213
#214
#215
0&
#216
#217
#218
#219
#220
b00001101 #
b00001101 $
b00011010 %
1&
b00001101 (
b00001101 )
#221
#222
#223
#224
#225
0&
#226
#227
#228
#229
#230
b00001110 #
b00001110 $
b00011100 %
1&
b00001110 (
b00001110 )
#231
#232
#233
#234
#235
0&
#236
#237
#238
#239
#240
b00001111 #
b00001111 $
b00011110 %
1&
b00001111 (
b00001111 )
#241
#242
#243
#244
#245
0&
#246
#247
#248
#249
#250
b00010000 #
b00010000 $
b00100000 %
1&
b00010000 (
b00010000 )
#251
#252
#253
#254
#255
0&
#256
#257
#258
#259
#260
b00010001 #
b00010001 $
b00100010 %
1&
b00010001 (
b00010001 )
#261
#262
#263
#264
#265
0&
#266
#267
#268
#269
#270
b00010010 #
b00010010 $
b00100100 %
1&
b00010010 (
b00010010 )
#271
#272
#273
#274
#275
0&
#276
#277
#278
#279
#280
b00010011 #
b00010011 $
b00100110 %
1&
b00010011 (
b00010011 )
#281
#282
#283
#284
#285
0&
#286
#287
#288
#289
#290
b00010100 #
b00010100 $
b00101000 %
1&
b00010100 (
b00010100 )
#291
#292
#293
#294
#295
0&
#296
#297
#298
#299
#300
b00010101 #
b00010101 $
b00101010 %
1&
b00010101 (
b00010101 )
#301
#302
#303
#304
#305
0&
#306
#307
#308
#309
#310
b00010110 #
b00010110 $
b00101100 %
1&
b00010110 (
b00010110 )
#311
#312
#313
#314
#315
0&
#316
#317
#318
#319
#320
b00010111 #
b00010111 $
b00101110 %
1&
b00010111 (
b00010111 )
#321
#322
#323
#324
#325
0&
#326
#327
#328
#329
#330
b00011000 #
b00011000 $
b00110000 %
1&
b00011000 (
b00011000 )
#331
#332
#333
#334
#335
0&
#336
#337
#338
#339
#340
b00011001 #
b00011001 $
b00110010 %
1&
b00011001 (
b00011001 )
#341
#342
#343
#344
#345
0&
#346
#347
#348
#349
#350
b00011010 #
b00011010 $
b00110100 %
1&
b00011010 (
b00011010 )
#351
#352
#353
#354
#355
0&
#356
#357
#358
#359
#360
b00011011 #
b00011011 $
b00110110 %
1&
b00011011 (
b00011011 )
#361
#362
#363
#364
#365
0&
#366
#367
#368
#369
#370
b00011100 #
b00011100 $
b00111000 %
1&
b00011100 (
b00011100 )
#371
#372
#373
#374
#375
0&
#376
#377
#378
#379
#380
b00011101 #
b00011101 $
b00111010 %
1&
b00011101 (
b00011101 )
#381
#382
#383
#384
#385
0&
#386
#387
#388
#389
#390
b00011110 #
b00011110 $
b00111100 %
1&
b00011110 (
b00011110 )
#391
#392
#393
#394
#395
0&
#396
#397
#398
#399
#400
b00011111 #
b00011111 $
b00111110 %
1&
b00011111 (
b00011111 )
#401
#402
#403
#404
#405
0&
#406
#407
#408
#409
#410
b00100000 #
b00100000 $
b01000000 %
1&
b00100000 (
b00100000 )
#411
#412
#413
#414
#415
0&
#416
#417
#418
#419
#420
b00100001 #
b00100001 $
b01000010 %
1&
b00100001 (
b00100001 )
#421
#422
#423
#424
#425
0&
#426
#427
#428
#429
#430
b00100010 #
b00100010 $
b01000100 %
1&
b00100010 (
b00100010 )
#431
#432
#433
#434
#435
0&
#436
#437
#438
#439
#440
b00100011 #
b00100011 $
b01000110 %
1&
b00100011 (
b00100011 )
#441
#442
#443
#444
#445
0&
#446
#447
#448
#449
#450
b00100100 #
b00100100 $
b01001000 %
1&
b00100100 (
b00100100 )
#451
#452
#453
#454
#455
0&
#456
#457
#458
#459
#460
b00100101 #
b00100101 $
b01001010 %
1&
b00100101 (
b00100101 )
#461
#462
#463
#464
#465
0&
#466
#467
#468
#469
#470
b00100110 #
b00100110 $
b01001100 %
1&
b00100110 (
b00100110 )
#471
#472
#473
#474
#475
0&
#476
#477
#478
#479
#480
b00100111 #
b00100111 $
b01001110 %
1&
b00100111 (
b00100111 )
#481
#482
#483
#484
#485
0&
#486
#487
#488
#489
#490
b00101000 #
b00101000 $
b01010000 %
1&
b00101000 (
b00101000 )
#491
#492
#493
#494
#495
0&
#496
#497
#498
#499
#500
b00101001 #
b00101001 $
b01010010 %
1&
b00101001 (
b00101001 )
#501
#502
#503
#504
#505
0&
#506
#507
#508
#509
#510
b00101010 #
b00101010 $
b01010100 %
1&
b00101010 (
b00101010 )
#511
#512
#513
#514
#515
0&
#516
#517
#518
#519
#520
b00101011 #
b00101011 $
b01010110 %
1&
b00101011 (
b00101011 )
#521
#522
#523
#524
#525
0&
#526
#527
#528
#529
#530
b00101100 #
b00101100 $
b01011000 %
1&
b00101100 (
b00101100 )
#531
#532
#533
#534
#535
0&
#536
#537
#538
#539
#540
b00101101 #
b00101101 $
b01011010 %
1&
b00101101 (
b00101101 )
#541
#542
#543
#544
#545
0&
#546
#547
#548
#549
#550
b00101110 #
b00101110 $
b01011100 %
1&
b00101110 (
b00101110 )
#551
#552
#553
#554
#555
0&
#556
#557
#558
#559
#560
b00101111 #
b00101111 $
b01011110 %
1&
b00101111 (
b00101111 )
#561
#562
#563
#564
#565
0&
#566
#567
#568
#569
#570
b00110000 #
b00110000 $
b01100000 %
1&
b00110000 (
b00110000 )
#571
#572
#573
#574
#575
0&
#576
#577
#578
#579
#580
b00110001 #
b00110001 $
b01100010 %
1&
b00110001 (
b00110001 )
#581
#582
#583
#584
#585
0&
#586
#587
#588
#589
#590
b00110010 #
b00110010 $
b01100100 %
1&
b00110010 (
b00110010 )
#591
#592
#593
#594
#595
0&
#596
#597
#598
#599
#600
b00110011 #
b00110011 $
b01100110 %
1&
b00110011 (
b00110011 )
#601
#602
#603
#604
#605
0&
#606
#607
#608
#609
#610
b00110100 #
b00110100 $
b01101000 %
1&
b00110100 (
b00110100 )
#611
#612
#613
#614
#615
0&
#616
#617
#618
#619
#620
b00110101 #
b00110101 $
b01101010 %
1&
b00110101 (
b00110101 )
#621
#622
#623
#624
#625
0&
#626
#627
#628
#629
#630
b00110110 #
b00110110 $
b01101100 %
1&
b00110110 (
b00110110 )
#631
#632
#633
#634
#635
0&
#636
#637
#638
#639
#640
b00110111 #
b00110111 $
b01101110 %
1&
b00110111 (
b00110111 )
#641
#642
#643
#644
#645
0&
#646
#647
#648
#649
#650
b00111000 #
b00111000 $
b01110000 %
1&
b00111000 (
b00111000 )
#651
#652
#653
#654
#655
0&
#656
#657
#658
#659
#660
b00111001 #
b00111001 $
b01110010 %
1&
b00111001 (
b00111001 )
#661
#662
#663
#664
#665
0&
#666
#667
#668
#669
#670
b00111010 #
b00111010 $
b01110100 %
1&
b00111010 (
b00111010 )
#671
#672
#673
#674
#675
0&
#676
#677
#678
#679
#680
b00111011 #
b00111011 $
b01110110 %
1&
b00111011 (
b00111011 )
#681
#682
#683
#684
#685
0&
#686
#687
#688
#689
#690
b00111100 #
b00111100 $
b01111000 %
1&
b00111100 (
b00111100 )
#691
#692
#693
#694
#695
0&
#696
#697
#698
#699
#700
b00111101 #
b00111101 $
b01111010 %
1&
b00111101 (
b00111101 )
#701
#702
#703
#704
#705
0&
#706
#707
#708
#709
#710
b00111110 #
b00111110 $
b01111100 %
1&
b00111110 (
b00111110 )
#711
#712
#713
#714
#715
0&
#716
#717
#718
#719
#720
b00111111 #
b00111111 $
b01111110 %
1&
b00111111 (
b00111111 )
#721
#722
#723
#724
#725
0&
#726
#727
#728
#729
#730
b01000000 #
b01000000 $
b10000000 %
1&
b01000000 (
b01000000 )
#731
#732
#733
#734
#735
0&
#736
#737
#738
#739
#740
b01000001 #
b01000001 $
b10000010 %
1&
b01000001 (
b01000001 )
#741
#742
#743
#744
#745
0&
#746
#747
#748
#749
#750
b01000010 #
b01000010 $
b10000100 %
1&
b01000010 (
b01000010 )
#751
#752
#753
#754
#755
0&
#756
#757
#758
#759
#760
b01000011 #
b01000011 $
b10000110 %
1&
b01000011 (
b01000011 )
#761
#762
#763
#764
#765
0&
#766
#767
#768
#769
#770
b01000100 #
b01000100 $
b10001000 %
1&
b01000100 (
b01000100 )
#771
#772
#773
#774
#775
0&
#776
#777
#778
#779
#780
b01000101 #
b01000101 $
b10001010 %
1&
b01000101 (
b01000101 )
#781
#782
#783
#784
#785
0&
#786
#787
#788
#789
#790
b01000110 #
b01000110 $
b10001100 %
1&
b01000110 (
b01000110 )
#791
#792
#793
#794
#795
0&
#796
#797
#798
#799
#800
b01000111 #
b01000111 $
b10001110 %
1&
b01000111 (
b01000111 )
#801
#802
#803
#804
#805
0&
#806
#807
#808
#809
#810
b01001000 #
b01001000 $
b10010000 %
1&
b01001000 (
b01001000 )
#811
#812
#813
#814
#815
0&
#816
#817
#818
#819
#820
b01001001 #
b01001001 $
b10010010 %
1&
b01001001 (
b01001001 )
#821
#822
#823
#824
#825
0&
#826
#827
#828
#829
#830
b01001010 #
b01001010 $
b10010100 %
1&
b01001010 (
b01001010 )
#831
#832
#833
#834
#835
0&
#836
#837
#838
#839
#840
b01001011 #
b01001011 $
b10010110 %
1&
b01001011 (
b01001011 )
#841
#842
#843
#844
#845
0&
#846
#847
#848
#849
#850
b01001100 #
b01001100 $
b10011000 %
1&
b01001100 (
b01001100 )
#851
#852
#853
#854
#855
0&
#856
#857
#858
#859
#860
b01001101 #
b01001101 $
b10011010 %
1&
b01001101 (
b01001101 )
#861
#862
#863
#864
#865
0&
#866
#867
#868
#869
#870
b01001110 #
b01001110 $
b10011100 %
1&
b01001110 (
b01001110 )
#871
#872
#873
#874
#875
0&
#876
#877
#878
#879
#880
b01001111 #
b01001111 $
b10011110 %
1&
b01001111 (
b01001111 )
#881
#882
#883
#884
#885
0&
#886
#887
#888
#889
#890
b01010000 #
b01010000 $
b10100000 %
1&
b01010000 (
b01010000 )
#891
#892
#893
#894
#895
0&
#896
#897
#898
#899
#900
b01010001 #
b01010001 $
b10100010 %
1&
b01010001 (
b01010001 )
#901
#902
#903
#904
#905
0&
#906
#907
#908
#909
#910
b01010010 #
b01010010 $
b10100100 %
1&
b01010010 (
b01010010 )
#911
#912
#913
#914
#915
0&
#916
#917
#918
#919
#920
b01010011 #
b01010011 $
b10100110 %
1&
b01010011 (
b01010011 )
#921
#922
#923
#924
#925
0&
#926
#927
#928
#929
#930
b01010100 #
b01010100 $
b10101000 %
1&
b01010100 (
b01010100 )
#931
#932
#933
#934
#935
0&
#936
#937
#938
#939
#940
b01010101 #
b01010101 $
b10101010 %
1&
b01010101 (
b01010101 )
#941
#942
#943
#944
#945
0&
#946
#947
#948
#949
#950
b01010110 #
b01010110 $
b10101100 %
1&
b01010110 (
b01010110 )
#951
#952
#953
#954
#955
0&
#956
#957
#958
#959
#960
b01010111 #
b01010111 $
b10101110 %
1&
b01010111 (
b01010111 )
#961
#962
#963
#964
#965
0&
#966
#967
#968
#969
#970
b01011000 #
b01011000 $
b10110000 %
1&
b01011000 (
b01011000 )
#971
#972
#973
#974
#975
0&
#976
#977
#978
#979
#980
b01011001 #
b01011001 $
b10110010 %
1&
b01011001 (
b01011001 )
#981
#982
#983
#984
#985
0&
#986
#987
#988
#989
#990
b01011010 #
b01011010 $
b10110100 %
1&
b01011010 (
b01011010 )
#991
#992
#993
#994
#995
0&
#996
#997
#998
#999
#1000
b01011011 #
b01011011 $
b10110110 %
1&
b01011011 (
b01011011 )
#1001
#1002
#1003
#1004
#1005
0&
#1006
#1007
#1008
#1009
#1010
b01011100 #
b01011100 $
b10111000 %
1&
b01011100 (
b01011100 )
#1011
#1012
#1013
#1014
#1015
0&
#1016
#1017
#1018
#1019
#1020
b01011101 #
b01011101 $
b10111010 %
1&
b01011101 (
b01011101 )
#1021
#1022
#1023
#1024
#1025
0&
#1026
#1027
#1028
#1029
#1030
b01011110 #
b01011110 $
b10111100 %
1&
b01011110 (
b01011110 )
#1031
#1032
#1033
#1034
#1035
0&
#1036
#1037
#1038
#1039
#1040
b01011111 #
b01011111 $
b10111110 %
1&
b01011111 (
b01011111 )
#1041
#1042
#1043
#1044
#1045
0&
#1046
#1047
#1048
#1049
#1050
b01100000 #
b01100000 $
b11000000 %
1&
b01100000 (
b01100000 )
#1051
#1052
#1053
#1054
#1055
0&
#1056
#1057
#1058
#1059
#1060
b01100001 #
b01100001 $
b11000010 %
1&
b01100001 (
b01100001 )
#1061
#1062
#1063
#1064
#1065
0&
#1066
#1067
#1068
#1069
#1070
b01100010 #
b01100010 $
b11000100 %
1&
b01100010 (
b01100010 )
#1071
#1072
#1073
#1074
#1075
0&
#1076
#1077
#1078
#1079
#1080
b01100011 #
b01100011 $
b11000110 %
1&
b01100011 (
b01100011 )
#1081
#1082
#1083
#1084
#1085
0&
#1086
#1087
#1088
#1089
#1090
b01100100 #
b01100100 $
b11001000 %
1&
b01100100 (
b01100100 )
